zyf_timer/__init__.py
zyf_timer/timer.py
zyf_timer-1.8.dist-info/LICENSE
zyf_timer-1.8.dist-info/METADATA
zyf_timer-1.8.dist-info/WHEEL
zyf_timer-1.8.dist-info/top_level.txt
zyf_timer-1.8.dist-info/RECORD
