Metadata-Version: 2.1
Name: zyf-timer
Version: 1.8
Summary: 计时器
Home-page: UNKNOWN
Author: zhangyafei
Author-email: zhangyafeii@foxmail.com
License: UNKNOWN
Platform: UNKNOWN
Classifier: Programming Language :: Python :: 3
Classifier: License :: OSI Approved :: MIT License
Classifier: Operating System :: OS Independent
Requires-Python: >=3.6
Requires-Dist: prettytable
